intelepy
